{"_type":"export","__export_format":4,"__export_date":"2022-12-14T18:01:08.086Z","__export_source":"insomnia.desktop.app:v2022.6.0","resources":[{"_id":"req_37e41326f7704546973652b7eed5b6f9","parentId":"wrk_d7024c7ce40045d49bcd3850f04bdcda","modified":1671040541361,"created":1671034557488,"url":"http://localhost:4000/api/v1/mantenimiento/addtecnico","name":"addtecnico","description":"","method":"POST","body":{"mimeType":"application/json","text":"{\n\t\"Nombre\": \"Raul\",\n\t\"Apellido\": \"Navarrete\",\n\t\"Activo\": \"S\"\n}"},"parameters":[],"headers":[{"name":"Content-Type","value":"application/json"}],"authentication":{},"metaSortKey":-1671034557488,"isPrivate":false,"settingStoreCookies":true,"settingSendCookies":true,"settingDisableRenderRequestBody":false,"settingEncodeUrl":true,"settingRebuildPath":true,"settingFollowRedirects":"global","_type":"request"},{"_id":"wrk_d7024c7ce40045d49bcd3850f04bdcda","parentId":null,"modified":1671034557351,"created":1671034557351,"name":"New Document","description":"","scope":"design","_type":"workspace"},{"_id":"req_0c08fb09b49645bc94af30029bc54b5e","parentId":"wrk_d7024c7ce40045d49bcd3850f04bdcda","modified":1671040538395,"created":1671039119590,"url":"http://localhost:4000/api/v1/mantenimiento/addregistro","name":"addregistro","description":"","method":"POST","body":{"mimeType":"application/json","text":"{\n\t\"Nombre\": \"Misa\",\n\t\"Departamento\": \"Sistemas\",\n\t\"Categoria\": \"Hardware\",\n\t\"Recurso\": \"Computador i3\",\n\t\"Emitido\": \"2023-05-25\",\n\t\"Estado\": \"Asignado\",\n\t\"Prioridad\": \"Critico\", \n\t\"Calificacion\": \"Pendiente\", \n\t\"Supervisor\": \"Raul\", \n\t\"Registrado\": \"s\"\n        \n}"},"parameters":[],"headers":[{"name":"Content-Type","value":"application/json"}],"authentication":{},"metaSortKey":-1671034557463,"isPrivate":false,"settingStoreCookies":true,"settingSendCookies":true,"settingDisableRenderRequestBody":false,"settingEncodeUrl":true,"settingRebuildPath":true,"settingFollowRedirects":"global","_type":"request"},{"_id":"req_0de6079022c048fa89992e5627df0be9","parentId":"wrk_d7024c7ce40045d49bcd3850f04bdcda","modified":1671040539049,"created":1671035263516,"url":"http://localhost:4000/api/v1/mantenimiento/gettecnico","name":"gettecnico","description":"","method":"GET","body":{"mimeType":"application/json","text":"{\n\t\"Nombre\": \"Raul\",\n\t\"Apellido\": \"Navarrete\",\n\t\"Activo\": \"S\"\n}"},"parameters":[],"headers":[{"name":"Content-Type","value":"application/json"}],"authentication":{},"metaSortKey":-1671034557438,"isPrivate":false,"settingStoreCookies":true,"settingSendCookies":true,"settingDisableRenderRequestBody":false,"settingEncodeUrl":true,"settingRebuildPath":true,"settingFollowRedirects":"global","_type":"request"},{"_id":"req_f91326a2079f4afb8df4e43203e3825c","parentId":"wrk_d7024c7ce40045d49bcd3850f04bdcda","modified":1671040518084,"created":1671040506171,"url":"http://localhost:4000/api/v1/mantenimiento/getregistro","name":"getregistro","description":"","method":"GET","body":{"mimeType":"application/json","text":""},"parameters":[],"headers":[{"name":"Content-Type","value":"application/json"}],"authentication":{},"metaSortKey":-1671034557413,"isPrivate":false,"settingStoreCookies":true,"settingSendCookies":true,"settingDisableRenderRequestBody":false,"settingEncodeUrl":true,"settingRebuildPath":true,"settingFollowRedirects":"global","_type":"request"},{"_id":"req_3584c45098f74ca8a88819c202f9e87a","parentId":"wrk_d7024c7ce40045d49bcd3850f04bdcda","modified":1671040539823,"created":1671035882774,"url":"http://localhost:4000/api/v1/mantenimiento/updtecnico/id/1","name":"updtecnico","description":"","method":"PUT","body":{"mimeType":"application/json","text":"{\n\t\"Nombre\": \"Misa\",\n\t\"Apellido\": \"Yamasaki\",\n\t\"Activo\": \"S\"\n}"},"parameters":[],"headers":[{"name":"Content-Type","value":"application/json"}],"authentication":{},"metaSortKey":-1671034557388,"isPrivate":false,"settingStoreCookies":true,"settingSendCookies":true,"settingDisableRenderRequestBody":false,"settingEncodeUrl":true,"settingRebuildPath":true,"settingFollowRedirects":"global","_type":"request"},{"_id":"req_9fa45f33846d4a529f02434297823a1d","parentId":"wrk_d7024c7ce40045d49bcd3850f04bdcda","modified":1671036614033,"created":1671036477416,"url":"http://localhost:4000/api/v1/mantenimiento/deltecnico/id/1","name":"deltecnico","description":"","method":"DELETE","body":{"mimeType":"application/json","text":""},"parameters":[],"headers":[{"name":"Content-Type","value":"application/json"}],"authentication":{},"metaSortKey":-1671034557338,"isPrivate":false,"settingStoreCookies":true,"settingSendCookies":true,"settingDisableRenderRequestBody":false,"settingEncodeUrl":true,"settingRebuildPath":true,"settingFollowRedirects":"global","_type":"request"},{"_id":"env_8ee7ac34e5ad444c981d9a36ba627a389f7f415d","parentId":"wrk_d7024c7ce40045d49bcd3850f04bdcda","modified":1671034557481,"created":1671034557481,"name":"Base Environment","data":{},"dataPropertyOrder":null,"color":null,"isPrivate":false,"metaSortKey":1671034557481,"_type":"environment"},{"_id":"jar_8ee7ac34e5ad444c981d9a36ba627a389f7f415d","parentId":"wrk_d7024c7ce40045d49bcd3850f04bdcda","modified":1671034557484,"created":1671034557484,"name":"Default Jar","cookies":[],"_type":"cookie_jar"},{"_id":"spc_83faa1eb5a4f4a26b6b3642cf00916cb","parentId":"wrk_d7024c7ce40045d49bcd3850f04bdcda","modified":1671034557364,"created":1671034557364,"fileName":"New Document","contents":"","contentType":"yaml","_type":"api_spec"},{"_id":"uts_e3ef6d72aff5420fa9b27ae46668a838","parentId":"wrk_d7024c7ce40045d49bcd3850f04bdcda","modified":1671034557490,"created":1671034557490,"name":"Example Test Suite","_type":"unit_test_suite"}]}